occasion_analysis_package/__init__.py
occasion_analysis_package/emoji_chart.py
occasion_analysis_package/export_data.py
occasion_analysis_package/word_cloud.py
occasion_analysis_package-2.9.dist-info/METADATA
occasion_analysis_package-2.9.dist-info/WHEEL
occasion_analysis_package-2.9.dist-info/top_level.txt
occasion_analysis_package-2.9.dist-info/RECORD
