Metadata-Version: 2.1
Name: occasion-analysis-package
Version: 2.9
Summary: Python package to do analysis on Occasion
Author: Anjali Mangla
Author-email: anjali.m@touchnote.in
License: MIT
Classifier: Intended Audience :: Developers
Classifier: Programming Language :: Python :: 3.9
Classifier: Operating System :: Microsoft :: Windows
Requires-Dist: psycopg2
Requires-Dist: pandas
Requires-Dist: python-dotenv
Requires-Dist: numpy
Requires-Dist: matplotlib
Requires-Dist: spacy
Requires-Dist: sklearn
Requires-Dist: plotly
Requires-Dist: advertools
Requires-Dist: wordcloud
